ShenruLijieNodeJsHexinsixiangYuYuanmaFenxi/README.md
ShenruLijieNodeJsHexinsixiangYuYuanmaFenxi/__init__.py
ShenruLijieNodeJsHexinsixiangYuYuanmaFenxi/__main__.py
ShenruLijieNodeJsHexinsixiangYuYuanmaFenxi/file.epub
ShenruLijieNodeJsHexinsixiangYuYuanmaFenxi/index.html
ShenruLijieNodeJsHexinsixiangYuYuanmaFenxi/css/__init__.py
ShenruLijieNodeJsHexinsixiangYuYuanmaFenxi/css/annotations.css
ShenruLijieNodeJsHexinsixiangYuYuanmaFenxi/css/main.css
ShenruLijieNodeJsHexinsixiangYuYuanmaFenxi/css/normalize.css
ShenruLijieNodeJsHexinsixiangYuYuanmaFenxi/css/popup.css
ShenruLijieNodeJsHexinsixiangYuYuanmaFenxi/font/__init__.py
ShenruLijieNodeJsHexinsixiangYuYuanmaFenxi/font/fontello.eot
ShenruLijieNodeJsHexinsixiangYuYuanmaFenxi/font/fontello.svg
ShenruLijieNodeJsHexinsixiangYuYuanmaFenxi/font/fontello.ttf
ShenruLijieNodeJsHexinsixiangYuYuanmaFenxi/font/fontello.woff
ShenruLijieNodeJsHexinsixiangYuYuanmaFenxi/img/__init__.py
ShenruLijieNodeJsHexinsixiangYuYuanmaFenxi/img/annotator-glyph-sprite.png
ShenruLijieNodeJsHexinsixiangYuYuanmaFenxi/img/annotator-icon-sprite.png
ShenruLijieNodeJsHexinsixiangYuYuanmaFenxi/img/apple-touch-icon.png
ShenruLijieNodeJsHexinsixiangYuYuanmaFenxi/img/cancelfullscreen.png
ShenruLijieNodeJsHexinsixiangYuYuanmaFenxi/img/close.png
ShenruLijieNodeJsHexinsixiangYuYuanmaFenxi/img/fullscreen.png
ShenruLijieNodeJsHexinsixiangYuYuanmaFenxi/img/loader.gif
ShenruLijieNodeJsHexinsixiangYuYuanmaFenxi/img/menu-icon.png
ShenruLijieNodeJsHexinsixiangYuYuanmaFenxi/img/save.png
ShenruLijieNodeJsHexinsixiangYuYuanmaFenxi/img/saved.png
ShenruLijieNodeJsHexinsixiangYuYuanmaFenxi/img/settings-s.png
ShenruLijieNodeJsHexinsixiangYuYuanmaFenxi/img/settings.png
ShenruLijieNodeJsHexinsixiangYuYuanmaFenxi/img/star.png
ShenruLijieNodeJsHexinsixiangYuYuanmaFenxi/js/__init__.py
ShenruLijieNodeJsHexinsixiangYuYuanmaFenxi/js/epub.js
ShenruLijieNodeJsHexinsixiangYuYuanmaFenxi/js/epub.min.js
ShenruLijieNodeJsHexinsixiangYuYuanmaFenxi/js/epub.min.map
shenru_lijie_node_js_hexinsixiang_yu_yuanma_fenxi-2024.3.1.0.dist-info/METADATA
shenru_lijie_node_js_hexinsixiang_yu_yuanma_fenxi-2024.3.1.0.dist-info/WHEEL
shenru_lijie_node_js_hexinsixiang_yu_yuanma_fenxi-2024.3.1.0.dist-info/entry_points.txt
shenru_lijie_node_js_hexinsixiang_yu_yuanma_fenxi-2024.3.1.0.dist-info/top_level.txt
shenru_lijie_node_js_hexinsixiang_yu_yuanma_fenxi-2024.3.1.0.dist-info/RECORD
